README.md
setup.py
foxhole_warapi_client.egg-info/PKG-INFO
foxhole_warapi_client.egg-info/SOURCES.txt
foxhole_warapi_client.egg-info/dependency_links.txt
foxhole_warapi_client.egg-info/requires.txt
foxhole_warapi_client.egg-info/top_level.txt
test/__init__.py
test/test_external_api.py
test/test_faction_enum.py
test/test_map.py
test/test_map_item.py
test/test_map_text_items.py
test/test_maps_api.py
test/test_server_connection_info.py
test/test_shard_status.py
test/test_war.py
test/test_war_api.py
test/test_war_report.py
warapi_client/__init__.py
warapi_client/api_client.py
warapi_client/configuration.py
warapi_client/rest.py
warapi_client/api/__init__.py
warapi_client/api/external_api.py
warapi_client/api/maps_api.py
warapi_client/api/war_api.py
warapi_client/models/__init__.py
warapi_client/models/faction_enum.py
warapi_client/models/map.py
warapi_client/models/map_item.py
warapi_client/models/map_text_items.py
warapi_client/models/server_connection_info.py
warapi_client/models/shard_status.py
warapi_client/models/war.py
warapi_client/models/war_report.py