Metadata-Version: 2.1
Name: foxhole-warapi-client
Version: 1.0.0
Summary: WarAPI
Home-page: https://github.com/Opa-/foxhole-warapi-python-client
Author-email: 
Keywords: Swagger,WarAPI
Requires-Dist: urllib3>=1.15
Requires-Dist: six>=1.10
Requires-Dist: certifi
Requires-Dist: python-dateutil
